odoo10_addon_account_bank_statement_import_camt-10.0.1.1.6-py2.7-nspkg.pth
odoo/addons/account_bank_statement_import_camt/README.rst
odoo/addons/account_bank_statement_import_camt/__init__.py
odoo/addons/account_bank_statement_import_camt/__manifest__.py
odoo/addons/account_bank_statement_import_camt/i18n/account_bank_statement_import_camt.pot
odoo/addons/account_bank_statement_import_camt/i18n/account_bank_statement_import_camt_oca.pot
odoo/addons/account_bank_statement_import_camt/i18n/de.po
odoo/addons/account_bank_statement_import_camt/i18n/es.po
odoo/addons/account_bank_statement_import_camt/i18n/fi.po
odoo/addons/account_bank_statement_import_camt/i18n/fr.po
odoo/addons/account_bank_statement_import_camt/i18n/fr_CH.po
odoo/addons/account_bank_statement_import_camt/i18n/gl.po
odoo/addons/account_bank_statement_import_camt/i18n/hr.po
odoo/addons/account_bank_statement_import_camt/i18n/lt_LT.po
odoo/addons/account_bank_statement_import_camt/i18n/nb_NO.po
odoo/addons/account_bank_statement_import_camt/i18n/nl.po
odoo/addons/account_bank_statement_import_camt/i18n/pt_BR.po
odoo/addons/account_bank_statement_import_camt/i18n/pt_PT.po
odoo/addons/account_bank_statement_import_camt/i18n/sl.po
odoo/addons/account_bank_statement_import_camt/models/__init__.py
odoo/addons/account_bank_statement_import_camt/models/account_bank_statement_import.py
odoo/addons/account_bank_statement_import_camt/models/parser.py
odoo/addons/account_bank_statement_import_camt/static/description/icon.png
odoo/addons/account_bank_statement_import_camt/test_files/golden-camt053-no-ntry.pydata
odoo/addons/account_bank_statement_import_camt/test_files/golden-camt053-txdtls.pydata
odoo/addons/account_bank_statement_import_camt/test_files/golden-camt053.pydata
odoo/addons/account_bank_statement_import_camt/test_files/test-camt053
odoo/addons/account_bank_statement_import_camt/test_files/test-camt053-no-ntry
odoo10_addon_account_bank_statement_import_camt-10.0.1.1.6.dist-info/METADATA
odoo10_addon_account_bank_statement_import_camt-10.0.1.1.6.dist-info/RECORD
odoo10_addon_account_bank_statement_import_camt-10.0.1.1.6.dist-info/WHEEL
odoo10_addon_account_bank_statement_import_camt-10.0.1.1.6.dist-info/namespace_packages.txt
odoo10_addon_account_bank_statement_import_camt-10.0.1.1.6.dist-info/top_level.txt
